aitclient/__init__.py
aitclient/auth.py
aitclient/upload.py
aitclient/certs/SAP_Global_Root.pem
aitclient-0.1.24.dist-info/LICENSE
aitclient-0.1.24.dist-info/METADATA
aitclient-0.1.24.dist-info/WHEEL
aitclient-0.1.24.dist-info/entry_points.txt
aitclient-0.1.24.dist-info/top_level.txt
aitclient-0.1.24.dist-info/RECORD
