Metadata-Version: 2.1
Name: aitclient
Version: 0.1.24
Summary: A Python library for AIT client operations
Home-page: https://github.com/I835834/aitclient
Author: Bobby Svidron
Author-email: bobby.svidron@sap.com
Classifier: Programming Language :: Python :: 3
Classifier: License :: OSI Approved :: MIT License
Classifier: Operating System :: OS Independent
Requires-Python: >=3.6
License-File: LICENSE
Requires-Dist: requests
Requires-Dist: pandas
